mapilio_kit/__init__.py
mapilio_kit/__main__.py
mapilio_kit/base/__init__.py
mapilio_kit/base/authenticate.py
mapilio_kit/base/decompose.py
mapilio_kit/base/gopro_360max.py
mapilio_kit/base/image_and_csv_upload.py
mapilio_kit/base/loader.py
mapilio_kit/base/process_csv.py
mapilio_kit/base/run.py
mapilio_kit/base/sampler.py
mapilio_kit/base/video_upload.py
mapilio_kit/base/zip.py
mapilio_kit/components/__init__.py
mapilio_kit/components/arguments.py
mapilio_kit/components/auth_config.py
mapilio_kit/components/config.py
mapilio_kit/components/edit_config.py
mapilio_kit/components/error.py
mapilio_kit/components/exif_metadata_reader.py
mapilio_kit/components/exif_metadata_writer.py
mapilio_kit/components/ffmpeg.py
mapilio_kit/components/geotag_property_handler.py
mapilio_kit/components/gpmf.py
mapilio_kit/components/gps_from_gopro360.py
mapilio_kit/components/gps_parser.py
mapilio_kit/components/gpx_from_exif.py
mapilio_kit/components/gpx_from_gopro.py
mapilio_kit/components/image_log.py
mapilio_kit/components/insert_MAPJson.py
mapilio_kit/components/interprocess_communication.py
mapilio_kit/components/login.py
mapilio_kit/components/metadata_property_handler.py
mapilio_kit/components/process_csv_to_description.py
mapilio_kit/components/processing.py
mapilio_kit/components/sequence_property_handler.py
mapilio_kit/components/types_fmt.py
mapilio_kit/components/upload.py
mapilio_kit/components/upload_manager.py
mapilio_kit/components/uploader.py
mapilio_kit/components/utilities.py
mapilio_kit/components/version.py
mapilio_kit/components/video_processor.py
mapilio_kit_v2-2.0.0.dist-info/LICENSE
mapilio_kit_v2-2.0.0.dist-info/METADATA
mapilio_kit_v2-2.0.0.dist-info/WHEEL
mapilio_kit_v2-2.0.0.dist-info/entry_points.txt
mapilio_kit_v2-2.0.0.dist-info/top_level.txt
mapilio_kit_v2-2.0.0.dist-info/RECORD
